nit_dpi_validator/__init__.py
nit_dpi_validator/dpi.py
nit_dpi_validator/nit.py
nit_dpi_validator-0.2.dist-info/LICENSE
nit_dpi_validator-0.2.dist-info/METADATA
nit_dpi_validator-0.2.dist-info/WHEEL
nit_dpi_validator-0.2.dist-info/top_level.txt
nit_dpi_validator-0.2.dist-info/RECORD
