Metadata-Version: 2.1
Name: nit-dpi-validator
Version: 0.2
Summary: Validador NIT, DPI Guatemala
Home-page: https://github.com/monroy95/nit_dpi_validator
Author: Mario Monroy Canizales
Author-email: m.monroyc22@hotmail.com
License: LGPL
Keywords: dpi,nit,Validador NIT Guatemala,NIT Guatemala,Validador DPI GT
Platform: UNKNOWN
Requires-Python: >=2.7
